bumimport/__init__.py
bumimport/strategies.py
bumimport-1.1.0.dist-info/METADATA
bumimport-1.1.0.dist-info/WHEEL
bumimport-1.1.0.dist-info/licenses/LICENSE.md
bumimport-1.1.0.dist-info/RECORD
