Metadata-Version: 2.4
Name: bumimport
Version: 1.1.0
Summary: A Python package for various lazy (discouraged) import strategies.
Project-URL: Repository, https://www.github.com/ryanbaekr/bumimport
Author: Ryan Baker
License-Expression: GPL-3.0-only
License-File: LICENSE.md
Classifier: License :: OSI Approved :: GNU General Public License v3 (GPLv3)
Classifier: Programming Language :: Python :: 3
Requires-Python: >=3.9
